exposan/__init__.py
exposan/utils.py
exposan/adm/README.rst
exposan/adm/__init__.py
exposan/adm/analyses.py
exposan/adm/model.py
exposan/adm/system.py
exposan/adm/data/_adm1.tsv
exposan/adm/data/stoichio.xlsx
exposan/asm/README.rst
exposan/asm/__init__.py
exposan/asm/systems.py
exposan/asm/validation.py
exposan/asm/data/_asm1.tsv
exposan/biogenic_refinery/README.rst
exposan/biogenic_refinery/__init__.py
exposan/biogenic_refinery/_components.py
exposan/biogenic_refinery/country_specific.py
exposan/biogenic_refinery/models.py
exposan/biogenic_refinery/systems.py
exposan/biogenic_refinery/uncertainty.py
exposan/biogenic_refinery/data/impact_indicators.csv
exposan/biogenic_refinery/data/impact_items.xlsx
exposan/bsm1/README.rst
exposan/bsm1/__init__.py
exposan/bsm1/analyses.py
exposan/bsm1/model.py
exposan/bsm1/system.py
exposan/bsm1/data/_asm1.tsv
exposan/bsm1/data/initial_conditions_asm1.xlsx
exposan/bsm1/data/initial_conditions_asm2d.xlsx
exposan/bsm1/data/matlab_exported_data_asm1.xlsx
exposan/bsm1/data/matlab_exported_data_asm2d.xlsx
exposan/bsm2/README.rst
exposan/bsm2/__init__.py
exposan/bsm2/system.py
exposan/bsm2/system_P.py
exposan/bsm2/data/adm1init.csv
exposan/bsm2/data/asm1init.csv
exposan/bsm2/data/bsm2p_init.xlsx
exposan/bsm2/data/settler1dinit.csv
exposan/bwaise/README.rst
exposan/bwaise/__init__.py
exposan/bwaise/_components.py
exposan/bwaise/_lca_data.py
exposan/bwaise/analyses.py
exposan/bwaise/models.py
exposan/bwaise/stats_demo.py
exposan/bwaise/systems.py
exposan/bwaise/data/LCA ReCiPe Damage to Points Unit Conversion.xlsx
exposan/bwaise/data/cf_dct.pckl
exposan/bwaise/data/indicators_new.tsv
exposan/bwaise/data/indicators_original.tsv
exposan/bwaise/data/items_original.xlsx
exposan/cas/README.rst
exposan/cas/__init__.py
exposan/cas/_components.py
exposan/cas/system.py
exposan/eco_san/README.rst
exposan/eco_san/__init__.py
exposan/eco_san/_components.py
exposan/eco_san/systems.py
exposan/eco_san/data/impact_indicators.tsv
exposan-1.4.3.dist-info/licenses/LICENSE.txt
exposan-1.4.3.dist-info/METADATA
exposan-1.4.3.dist-info/WHEEL
exposan-1.4.3.dist-info/top_level.txt
exposan-1.4.3.dist-info/RECORD
