Metadata-Version: 2.4
Name: exposan
Version: 1.4.3
Summary: Exposition of sanitation and resource recovery systems
Home-page: https://github.com/QSD-Group/EXPOsan
Author: Quantitative Sustainable Design Group
Author-email: quantitative.sustainable.design@gmail.com
License: UIUC
Project-URL: Homepage, https://qsdsan.com
Project-URL: Documentation, https://qsdsan.readthedocs.io
Project-URL: Repository, https://github.com/QSD-Group/EXPOsan
Keywords: quantitative sustainable design,sanitation,resource recovery,techno-economic analysis,life cycle assessment
Classifier: License :: OSI Approved :: University of Illinois/NCSA Open Source License
Classifier: Environment :: Console
Classifier: Topic :: Education
Classifier: Topic :: Scientific/Engineering
Classifier: Topic :: Scientific/Engineering :: Chemistry
Classifier: Topic :: Scientific/Engineering :: Mathematics
Classifier: Intended Audience :: Developers
Classifier: Intended Audience :: Education
Classifier: Intended Audience :: Manufacturing
Classifier: Intended Audience :: Science/Research
Classifier: Natural Language :: English
Classifier: Operating System :: OS Independent
Classifier: Programming Language :: Python :: 3.12
License-File: LICENSE.txt
Requires-Dist: qsdsan==1.4.3
Dynamic: author
Dynamic: author-email
Dynamic: classifier
Dynamic: description
Dynamic: home-page
Dynamic: keywords
Dynamic: license
Dynamic: license-file
Dynamic: project-url
Dynamic: requires-dist
Dynamic: summary
